{"name": "Belgische_vereniging", "id": 139870, "predecessors": [{"name": "Burgerlijk_recht", "id": 106862}, {"name": "Geomorfologie", "id": 482136}], "successors": [{"name": "Vlaamse_vereniging", "id": 1538203}, {"name": "Vereniging_zonder_winstoogmerk", "id": 4917703}, {"name": "Belgische_vrouwenvoetbalclub", "id": 3518797}, {"name": "Vlaamse_voetbalclub", "id": 5500172}, {"name": "Waalse_voetbalclub", "id": 5500174}, {"name": "RSC_Anderlecht_naar_seizoen", "id": 1341214}, {"name": "Belgische_band", "id": 107674}, {"name": "Belgisch_harmonieorkest", "id": 1243155}, {"name": "PS-politicus_(België)", "id": 1895708}, {"name": "Sportvereniging_in_Luik_(provincie)", "id": 5600624}, {"name": "Sportvereniging_in_Henegouwen", "id": 5600626}, {"name": "Sportvereniging_in_West-Vlaanderen", "id": 5600319}, {"name": "Sportvereniging_in_Oost-Vlaanderen", "id": 5600328}, {"name": "Sportvereniging_in_Antwerpen_(provincie)", "id": 5600329}, {"name": "Sportvereniging_in_Limburg_(België)", "id": 5600331}, {"name": "Sportvereniging_in_Vlaams-Brabant", "id": 5600332}]}