{"name": "Amerikaans_politicus", "id": 70114, "predecessors": [{"name": "Amerikaans_persoon", "id": 70053}, {"name": "Opleiding", "id": 135333}, {"name": "Beroep", "id": 63395}], "successors": [{"name": "Amerikaans_gouverneur", "id": 564115}, {"name": "President_van_de_Verenigde_Staten", "id": 701974}, {"name": "Vicepresident_van_de_Verenigde_Staten", "id": 1292064}, {"name": "Amerikaans_luitenant-gouverneur", "id": 2195825}, {"name": "Amerikaans_politicus_in_de_19e_eeuw", "id": 5633327}, {"name": "Deelnemer_aan_de_Amerikaanse_presidentsverkiezingen", "id": 5774897}, {"name": "Amerikaans_minister_van_Buitenlandse_Zaken", "id": 1497028}, {"name": "Lijsten_van_Amerikaanse_gouverneurs", "id": 904141}, {"name": "Lijsten_van_Amerikaanse_senatoren", "id": 1574736}, {"name": "Democraat_(Verenigde_Staten)", "id": 2087168}, {"name": "Republikein_(Verenigde_Staten)", "id": 2087169}, {"name": "Amerikaans_burgemeester", "id": 362073}]}