{"name": "Sociale_wetenschap", "id": 72308, "predecessors": [{"name": "Mens_en_maatschappij", "id": 176685}, {"name": "Alles", "id": 63579}], "successors": [{"name": "Sociologie", "id": 63383}, {"name": "Economie", "id": 63600}, {"name": "Geografie", "id": 63658}, {"name": "Psychologie", "id": 66843}, {"name": "Antropologie", "id": 67171}, {"name": "Demografie", "id": 72822}, {"name": "Politicologie", "id": 133143}, {"name": "Historiografie", "id": 546017}, {"name": "Organisatiekunde", "id": 2736344}, {"name": "Godsdienstfilosofie", "id": 1238766}, {"name": "Islamoloog", "id": 1773169}, {"name": "Conflict", "id": 99644}, {"name": "Management", "id": 79306}, {"name": "Semantiek", "id": 65119}, {"name": "Symbool", "id": 68313}, {"name": "Schriftteken", "id": 194161}, {"name": "Dogmatiek", "id": 1790899}, {"name": "Kerkvader", "id": 277118}, {"name": "Scholastisch_filosoof", "id": 1411024}, {"name": "Eschatologie", "id": 1758639}]}